{
  "_fv": 57,
  "_type": "recipe",
  "definition": {
    "recipeType": "Crafting",
    "recipeRetstackSize": 2,
    "group": "",
    "cookingBookCategory": "MISC",
    "xpReward": 0.0,
    "cookingTime": 200,
    "craftingBookCategory": "MISC",
    "recipeShapeless": false,
    "recipeSlots": [
      {
        "value": "Items.DIAMOND"
      },
      {
        "value": "CUSTOM:EnergiumUpgradeSmithingTemplate"
      },
      {
        "value": "Items.DIAMOND"
      },
      {
        "value": "Items.DIAMOND"
      },
      {
        "value": "CUSTOM:DepletedEnergiumBlock"
      },
      {
        "value": "Items.DIAMOND"
      },
      {
        "value": "Items.DIAMOND"
      },
      {
        "value": "Items.DIAMOND"
      },
      {
        "value": "Items.DIAMOND"
      }
    ],
    "recipeReturnStack": {
      "value": "CUSTOM:EnergiumUpgradeSmithingTemplate"
    },
    "name": "duplicate_energium_upgrade_smithing_template",
    "namespace": "mod"
  }
}