{
  "_fv": 55,
  "_type": "tool",
  "definition": {
    "toolType": "Axe",
    "renderType": 1,
    "blockingRenderType": 0,
    "texture": "tornado_axe",
    "customModelName": "tornado_axe:default",
    "blockingModelName": "Normal blocking",
    "name": "Tornado Axe",
    "specialInformation": {
      "fixedValue": []
    },
    "creativeTab": {
      "value": "No creative tab entry"
    },
    "harvestLevel": 4,
    "efficiency": 12.0,
    "attackSpeed": 1.09,
    "enchantability": 0,
    "damageVsEntity": 11.88,
    "usageCount": 0,
    "blocksAffected": [],
    "glowCondition": {
      "fixedValue": true
    },
    "repairItems": [],
    "immuneToFire": true,
    "stayInGridWhenCrafting": false,
    "damageOnCrafting": false,
    "onItemInInventoryTick": {
      "name": "TornadoAxeKazhdyiTikVInvientarie"
    }
  }
}