{
	"format_version": "1.8.0",
	"animations": {
		"cursed_squire.animation.idle": {
			"loop": true,
			"animation_length": 5.3333,
			"bones": {
				"bone7": {
					"rotation": {
						"0.0": {
							"post": {
								"vector": [0.32902, 7.49282, 2.52154]
							},
							"lerp_mode": "catmullrom"
						}
					}
				},
				"bone6": {
					"rotation": {
						"0.0": {
							"post": {
								"vector": [0.44067, -9.99038, -2.53852]
							},
							"lerp_mode": "catmullrom"
						}
					}
				},
				"bone4": {
					"rotation": {
						"0.0": {
							"post": {
								"vector": [0.10995, -7.49761, -2.51197]
							},
							"lerp_mode": "catmullrom"
						},
						"1.125": {
							"post": {
								"vector": [2.28224, -9.49048, -3.0067]
							},
							"lerp_mode": "catmullrom"
						},
						"2.0833": {
							"post": {
								"vector": [-2.43401, -7.49914, -1.50718]
							},
							"lerp_mode": "catmullrom"
						},
						"2.6667": {
							"post": {
								"vector": [0.10995, -7.49761, -2.51197]
							},
							"lerp_mode": "catmullrom"
						},
						"3.25": {
							"post": {
								"vector": [2.28224, -9.49048, -3.0067]
							},
							"lerp_mode": "catmullrom"
						},
						"3.5": {
							"post": {
								"vector": [-23.50006, 2.31335, -7.65724]
							},
							"lerp_mode": "catmullrom"
						},
						"3.8333": {
							"post": {
								"vector": [16.86931, -12.06196, -11.9681]
							},
							"lerp_mode": "catmullrom"
						},
						"4.1667": {
							"post": {
								"vector": [-23.50006, 2.31335, -7.65724]
							},
							"lerp_mode": "catmullrom"
						},
						"4.5": {
							"post": {
								"vector": [16.86931, -12.06196, -11.9681]
							},
							"lerp_mode": "catmullrom"
						},
						"4.8333": {
							"post": {
								"vector": [-23.50006, 2.31335, -7.65724]
							},
							"lerp_mode": "catmullrom"
						},
						"5.0833": {
							"post": {
								"vector": [16.86931, -12.06196, -11.9681]
							},
							"lerp_mode": "catmullrom"
						},
						"5.3333": {
							"post": {
								"vector": [0.10995, -7.49761, -2.51197]
							},
							"lerp_mode": "catmullrom"
						}
					},
					"position": {
						"0.0": {
							"post": {
								"vector": [0, 0, 0]
							},
							"lerp_mode": "catmullrom"
						},
						"1.25": {
							"post": {
								"vector": [0, -0.4, 0]
							},
							"lerp_mode": "catmullrom"
						},
						"2.6667": {
							"post": {
								"vector": [0, 0, 0]
							},
							"lerp_mode": "catmullrom"
						},
						"3.25": {
							"post": {
								"vector": [0, -0.4, 0]
							},
							"lerp_mode": "catmullrom"
						},
						"5.3333": {
							"post": {
								"vector": [0, 0, 0]
							},
							"lerp_mode": "catmullrom"
						}
					}
				},
				"bone3": {
					"rotation": {
						"0.0": {
							"post": {
								"vector": [0.10995, 7.49761, 2.51197]
							},
							"lerp_mode": "catmullrom"
						},
						"1.125": {
							"post": {
								"vector": [4.78224, 9.49048, 3.0067]
							},
							"lerp_mode": "catmullrom"
						},
						"2.0833": {
							"post": {
								"vector": [-2.43401, 7.49914, 1.50718]
							},
							"lerp_mode": "catmullrom"
						},
						"2.6667": {
							"post": {
								"vector": [0.10995, 7.49761, 2.51197]
							},
							"lerp_mode": "catmullrom"
						},
						"3.25": {
							"post": {
								"vector": [4.78224, 9.49048, 3.0067]
							},
							"lerp_mode": "catmullrom"
						},
						"3.5": {
							"post": {
								"vector": [16.86931, 12.06196, 11.9681]
							},
							"lerp_mode": "catmullrom"
						},
						"3.8333": {
							"post": {
								"vector": [-23.50006, -2.31335, 7.65724]
							},
							"lerp_mode": "catmullrom"
						},
						"4.1667": {
							"post": {
								"vector": [16.86931, 12.06196, 11.9681]
							},
							"lerp_mode": "catmullrom"
						},
						"4.5": {
							"post": {
								"vector": [-23.50006, -2.31335, 7.65724]
							},
							"lerp_mode": "catmullrom"
						},
						"4.8333": {
							"post": {
								"vector": [16.86931, 12.06196, 11.9681]
							},
							"lerp_mode": "catmullrom"
						},
						"5.0833": {
							"post": {
								"vector": [-23.50006, -2.31335, 7.65724]
							},
							"lerp_mode": "catmullrom"
						},
						"5.3333": {
							"post": {
								"vector": [0.10995, 7.49761, 2.51197]
							},
							"lerp_mode": "catmullrom"
						}
					},
					"position": {
						"0.0": {
							"post": {
								"vector": [0, 0, 0]
							},
							"lerp_mode": "catmullrom"
						},
						"1.25": {
							"post": {
								"vector": [0, -0.4, 0]
							},
							"lerp_mode": "catmullrom"
						},
						"2.6667": {
							"post": {
								"vector": [0, 0, 0]
							},
							"lerp_mode": "catmullrom"
						},
						"3.25": {
							"post": {
								"vector": [0, -0.4, 0]
							},
							"lerp_mode": "catmullrom"
						},
						"5.3333": {
							"post": {
								"vector": [0, 0, 0]
							},
							"lerp_mode": "catmullrom"
						}
					}
				},
				"bone5": {
					"rotation": {
						"0.0": {
							"post": {
								"vector": [0.5, 0, 0]
							},
							"lerp_mode": "catmullrom"
						},
						"0.875": {
							"post": {
								"vector": [0, 0, 0.5]
							},
							"lerp_mode": "catmullrom"
						},
						"1.375": {
							"post": {
								"vector": [-0.56213, 0, 0.0528]
							},
							"lerp_mode": "catmullrom"
						},
						"2.0417": {
							"post": {
								"vector": [0, 0, -0.5]
							},
							"lerp_mode": "catmullrom"
						},
						"2.6667": {
							"post": {
								"vector": [0.5, 0, 0]
							},
							"lerp_mode": "catmullrom"
						},
						"3.4583": {
							"post": {
								"vector": [0, 0, 0.5]
							},
							"lerp_mode": "catmullrom"
						},
						"3.75": {
							"post": {
								"vector": [-0.03611, 0.00637, 10.39215]
							},
							"lerp_mode": "catmullrom"
						},
						"3.8333": {
							"post": {
								"vector": [-0.03931, -9.99317, 2.29869]
							},
							"lerp_mode": "catmullrom"
						},
						"3.9583": {
							"post": {
								"vector": [-0.03611, 0.00637, -10.3921]
							},
							"lerp_mode": "catmullrom"
						},
						"4.0417": {
							"post": {
								"vector": [-0.03652, 10.72633, -2.49966]
							},
							"lerp_mode": "catmullrom"
						},
						"4.1667": {
							"post": {
								"vector": [-0.03611, 0.00637, 10.39215]
							},
							"lerp_mode": "catmullrom"
						},
						"4.25": {
							"post": {
								"vector": [-0.03673, -10.76547, 2.51422]
							},
							"lerp_mode": "catmullrom"
						},
						"4.375": {
							"post": {
								"vector": [-0.03611, 0.00637, -10.3921]
							},
							"lerp_mode": "catmullrom"
						},
						"4.4583": {
							"post": {
								"vector": [-0.03848, 10.78224, -2.99034]
							},
							"lerp_mode": "catmullrom"
						},
						"4.5833": {
							"post": {
								"vector": [-0.03611, 0.00637, 10.39215]
							},
							"lerp_mode": "catmullrom"
						},
						"4.7083": {
							"post": {
								"vector": [-0.04624, -10.78508, 7.59292]
							},
							"lerp_mode": "catmullrom"
						},
						"4.9167": {
							"post": {
								"vector": [0, 0, -0.5]
							},
							"lerp_mode": "catmullrom"
						},
						"5.3333": {
							"post": {
								"vector": [0.5, 0, 0]
							},
							"lerp_mode": "catmullrom"
						}
					},
					"position": {
						"3.4583": {
							"pre": {
								"vector": [0, 0, 0]
							},
							"post": {
								"vector": [0, 0, 0]
							},
							"lerp_mode": "catmullrom"
						},
						"3.625": {
							"post": {
								"vector": [0, -0.12, 0]
							},
							"lerp_mode": "catmullrom"
						},
						"3.75": {
							"post": {
								"vector": [0, 0.75, 0]
							},
							"lerp_mode": "catmullrom"
						},
						"3.875": {
							"post": {
								"vector": [0, -0.12, 0]
							},
							"lerp_mode": "catmullrom"
						},
						"4.0": {
							"post": {
								"vector": [0, 0.75, 0]
							},
							"lerp_mode": "catmullrom"
						},
						"4.125": {
							"post": {
								"vector": [0, -0.12, 0]
							},
							"lerp_mode": "catmullrom"
						},
						"4.25": {
							"post": {
								"vector": [0, 0.75, 0]
							},
							"lerp_mode": "catmullrom"
						},
						"4.375": {
							"post": {
								"vector": [0, -0.12, 0]
							},
							"lerp_mode": "catmullrom"
						},
						"4.5": {
							"post": {
								"vector": [0, 0.75, 0]
							},
							"lerp_mode": "catmullrom"
						},
						"4.625": {
							"post": {
								"vector": [0, -0.12, 0]
							},
							"lerp_mode": "catmullrom"
						},
						"4.75": {
							"post": {
								"vector": [0, 0.75, 0]
							},
							"lerp_mode": "catmullrom"
						},
						"4.875": {
							"post": {
								"vector": [0, -0.12, 0]
							},
							"lerp_mode": "catmullrom"
						},
						"5.0417": {
							"post": {
								"vector": [0, 0, 0]
							},
							"lerp_mode": "catmullrom"
						}
					}
				},
				"bone8": {
					"rotation": {
						"0.0": {
							"post": {
								"vector": [-1, 0, 0]
							},
							"lerp_mode": "catmullrom"
						},
						"0.7083": {
							"post": {
								"vector": [0, 0, -0.5]
							},
							"lerp_mode": "catmullrom"
						},
						"1.4583": {
							"post": {
								"vector": [1.38, 0, 0]
							},
							"lerp_mode": "catmullrom"
						},
						"1.9583": {
							"post": {
								"vector": [0, 0, 0.5]
							},
							"lerp_mode": "catmullrom"
						},
						"2.6667": {
							"post": {
								"vector": [-1, 0, 0]
							},
							"lerp_mode": "catmullrom"
						},
						"3.1667": {
							"post": {
								"vector": [0, 0, -0.5]
							},
							"lerp_mode": "catmullrom"
						},
						"3.4167": {
							"post": {
								"vector": [0.42496, 2.52083, -2.8864]
							},
							"lerp_mode": "catmullrom"
						},
						"3.625": {
							"post": {
								"vector": [0.42496, -2.52083, 2.8864]
							},
							"lerp_mode": "catmullrom"
						},
						"3.8333": {
							"post": {
								"vector": [0.42496, 2.52083, -2.8864]
							},
							"lerp_mode": "catmullrom"
						},
						"4.0417": {
							"post": {
								"vector": [0.42496, -2.52083, 2.8864]
							},
							"lerp_mode": "catmullrom"
						},
						"4.25": {
							"post": {
								"vector": [0.42496, 2.52083, -2.8864]
							},
							"lerp_mode": "catmullrom"
						},
						"4.4583": {
							"post": {
								"vector": [0.42496, -2.52083, 2.8864]
							},
							"lerp_mode": "catmullrom"
						},
						"4.6667": {
							"post": {
								"vector": [0.42496, 2.52083, -2.8864]
							},
							"lerp_mode": "catmullrom"
						},
						"4.875": {
							"post": {
								"vector": [-1, 0, 0]
							},
							"lerp_mode": "catmullrom"
						},
						"5.3333": {
							"post": {
								"vector": [-1, 0, 0]
							},
							"lerp_mode": "catmullrom"
						}
					},
					"position": {
						"0.0": {
							"post": {
								"vector": [0, 0, 0]
							},
							"lerp_mode": "catmullrom"
						},
						"1.25": {
							"post": {
								"vector": [0, -0.25, 0]
							},
							"lerp_mode": "catmullrom"
						},
						"1.7917": {
							"post": {
								"vector": [0, -0.25, 0]
							},
							"lerp_mode": "catmullrom"
						},
						"2.6667": {
							"post": {
								"vector": [0, 0, 0]
							},
							"lerp_mode": "catmullrom"
						},
						"3.4167": {
							"post": {
								"vector": [0, 0, 0]
							},
							"lerp_mode": "catmullrom"
						},
						"3.5417": {
							"post": {
								"vector": [0, -0.5, 0]
							},
							"lerp_mode": "catmullrom"
						},
						"3.6667": {
							"post": {
								"vector": [0, 0, 0]
							},
							"lerp_mode": "catmullrom"
						},
						"3.7917": {
							"post": {
								"vector": [0, -0.5, 0]
							},
							"lerp_mode": "catmullrom"
						},
						"3.9167": {
							"post": {
								"vector": [0, 0, 0]
							},
							"lerp_mode": "catmullrom"
						},
						"4.0417": {
							"post": {
								"vector": [0, -0.5, 0]
							},
							"lerp_mode": "catmullrom"
						},
						"4.1667": {
							"post": {
								"vector": [0, 0, 0]
							},
							"lerp_mode": "catmullrom"
						},
						"4.2917": {
							"post": {
								"vector": [0, -0.5, 0]
							},
							"lerp_mode": "catmullrom"
						},
						"4.4167": {
							"post": {
								"vector": [0, 0, 0]
							},
							"lerp_mode": "catmullrom"
						},
						"4.5417": {
							"post": {
								"vector": [0, -0.5, 0]
							},
							"lerp_mode": "catmullrom"
						},
						"4.6667": {
							"post": {
								"vector": [0, 0, 0]
							},
							"lerp_mode": "catmullrom"
						},
						"4.7917": {
							"post": {
								"vector": [0, -0.5, 0]
							},
							"lerp_mode": "catmullrom"
						},
						"4.9167": {
							"post": {
								"vector": [0, 0, 0]
							},
							"lerp_mode": "catmullrom"
						},
						"5.3333": {
							"post": {
								"vector": [0, 0, 0]
							},
							"lerp_mode": "catmullrom"
						}
					}
				}
			}
		},
		"cursed_squire.animation.walk": {
			"loop": true,
			"animation_length": 0.641,
			"bones": {
				"bone": {
					"position": {
						"0.0": {
							"post": {
								"vector": [0, 2, 0]
							},
							"lerp_mode": "catmullrom"
						},
						"0.2137": {
							"post": {
								"vector": [0, 0, 0]
							},
							"lerp_mode": "catmullrom"
						},
						"0.3205": {
							"post": {
								"vector": [0, 2, 0]
							},
							"lerp_mode": "catmullrom"
						},
						"0.5342": {
							"post": {
								"vector": [0, 0, 0]
							},
							"lerp_mode": "catmullrom"
						},
						"0.641": {
							"post": {
								"vector": [0, 2, 0]
							},
							"lerp_mode": "catmullrom"
						}
					}
				},
				"bone7": {
					"rotation": {
						"0.0": {
							"post": {
								"vector": [-22.5, 0, 0]
							},
							"lerp_mode": "catmullrom"
						},
						"0.3205": {
							"post": {
								"vector": [57.5, 0, 0]
							},
							"lerp_mode": "catmullrom"
						},
						"0.4808": {
							"post": {
								"vector": [0, 0, 0]
							},
							"lerp_mode": "catmullrom"
						},
						"0.641": {
							"post": {
								"vector": [-22.5, 0, 0]
							},
							"lerp_mode": "catmullrom"
						}
					},
					"position": {
						"0.0": {
							"post": {
								"vector": [0, -1.5, 0]
							},
							"lerp_mode": "catmullrom"
						},
						"0.1603": {
							"post": {
								"vector": [0, 0.13, 0]
							},
							"lerp_mode": "catmullrom"
						},
						"0.3205": {
							"post": {
								"vector": [0, 0, 0]
							},
							"lerp_mode": "catmullrom"
						},
						"0.4808": {
							"post": {
								"vector": [0, 3, -1]
							},
							"lerp_mode": "catmullrom"
						},
						"0.641": {
							"post": {
								"vector": [0, -1.5, 0]
							},
							"lerp_mode": "catmullrom"
						}
					}
				},
				"bone6": {
					"rotation": {
						"0.0": {
							"post": {
								"vector": [57.5, 0, 0]
							},
							"lerp_mode": "catmullrom"
						},
						"0.1603": {
							"post": {
								"vector": [0, 0, 0]
							},
							"lerp_mode": "catmullrom"
						},
						"0.3205": {
							"post": {
								"vector": [-37.5, 0, 0]
							},
							"lerp_mode": "catmullrom"
						},
						"0.641": {
							"post": {
								"vector": [57.5, 0, 0]
							},
							"lerp_mode": "catmullrom"
						}
					},
					"position": {
						"0.0": {
							"post": {
								"vector": [0, 0, 0]
							},
							"lerp_mode": "catmullrom"
						},
						"0.1603": {
							"post": {
								"vector": [0, 3, 0]
							},
							"lerp_mode": "catmullrom"
						},
						"0.3205": {
							"post": {
								"vector": [0, -0.5, -1]
							},
							"lerp_mode": "catmullrom"
						},
						"0.4808": {
							"post": {
								"vector": [0, -0.73, -0.45]
							},
							"lerp_mode": "catmullrom"
						},
						"0.641": {
							"post": {
								"vector": [0, 0, 0]
							},
							"lerp_mode": "catmullrom"
						}
					}
				},
				"bone4": {
					"rotation": {
						"0.0": {
							"post": {
								"vector": [-44.89078, -3.53329, -3.54002]
							},
							"lerp_mode": "catmullrom"
						},
						"0.1603": {
							"post": {
								"vector": [-74.56145, 7.05302, 7.10708]
							},
							"lerp_mode": "catmullrom"
						},
						"0.3205": {
							"post": {
								"vector": [-12.40773, 3.50444, -10.10573]
							},
							"lerp_mode": "catmullrom"
						},
						"0.4808": {
							"post": {
								"vector": [43.08187, 17.55472, -3.87355]
							},
							"lerp_mode": "catmullrom"
						},
						"0.641": {
							"post": {
								"vector": [-44.89078, -3.53329, -3.54002]
							},
							"lerp_mode": "catmullrom"
						}
					}
				},
				"bone3": {
					"rotation": {
						"0.0": {
							"post": {
								"vector": [44.89078, -3.53329, 3.54002]
							},
							"lerp_mode": "catmullrom"
						},
						"0.1603": {
							"post": {
								"vector": [54.8973, 4.09405, -2.87277]
							},
							"lerp_mode": "catmullrom"
						},
						"0.3205": {
							"post": {
								"vector": [0.18984, -1.61826, 11.24332]
							},
							"lerp_mode": "catmullrom"
						},
						"0.4808": {
							"post": {
								"vector": [-43.924, 5.21822, 5.3945]
							},
							"lerp_mode": "catmullrom"
						},
						"0.641": {
							"post": {
								"vector": [44.89078, -3.53329, 3.54002]
							},
							"lerp_mode": "catmullrom"
						}
					}
				},
				"bone5": {
					"rotation": {
						"0.0": {
							"post": {
								"vector": [-17.89807, -11.91276, 3.81397]
							},
							"lerp_mode": "catmullrom"
						},
						"0.1603": {
							"post": {
								"vector": [-27.22586, -12.74229, 1.77054]
							},
							"lerp_mode": "catmullrom"
						},
						"0.3205": {
							"post": {
								"vector": [-17.5, 0, 0]
							},
							"lerp_mode": "catmullrom"
						},
						"0.4808": {
							"post": {
								"vector": [-30.32893, 11.38682, -9.59296]
							},
							"lerp_mode": "catmullrom"
						},
						"0.641": {
							"post": {
								"vector": [-17.89807, -11.91276, 3.81397]
							},
							"lerp_mode": "catmullrom"
						}
					}
				},
				"bone8": {
					"rotation": {
						"0.0": {
							"post": {
								"vector": [22.61435, 9.91358, 1.31845]
							},
							"lerp_mode": "catmullrom"
						},
						"0.1603": {
							"post": {
								"vector": [22.67995, 12.39135, 1.6575]
							},
							"lerp_mode": "catmullrom"
						},
						"0.3205": {
							"post": {
								"vector": [22.5, 0, 0]
							},
							"lerp_mode": "catmullrom"
						},
						"0.4808": {
							"post": {
								"vector": [22.67995, -12.3914, 1.6575]
							},
							"lerp_mode": "catmullrom"
						},
						"0.641": {
							"post": {
								"vector": [22.61435, 9.91358, 1.31845]
							},
							"lerp_mode": "catmullrom"
						}
					}
				}
			}
		},
		"cursed_squire.animation.attack": {
			"animation_length": 0.5833,
			"bones": {
				"bone": {
					"rotation": {
						"0.0": {
							"post": {
								"vector": [0, 0, 0]
							},
							"lerp_mode": "catmullrom"
						},
						"0.1667": {
							"post": {
								"vector": [-7.5, -12.5, -7.5]
							},
							"lerp_mode": "catmullrom"
						},
						"0.3542": {
							"post": {
								"vector": [18.72518, 26.0728, 8.66015]
							},
							"lerp_mode": "catmullrom"
						},
						"0.4375": {
							"post": {
								"vector": [5.50528, 21.15906, -0.98621]
							},
							"lerp_mode": "catmullrom"
						},
						"0.5833": {
							"post": {
								"vector": [0, 0, 0]
							},
							"lerp_mode": "catmullrom"
						}
					},
					"position": {
						"0.0": {
							"post": {
								"vector": [0, 0, 0]
							},
							"lerp_mode": "catmullrom"
						},
						"0.1042": {
							"post": {
								"vector": [0, 2, -1]
							},
							"lerp_mode": "catmullrom"
						},
						"0.2917": {
							"post": {
								"vector": [0, 0, -1]
							},
							"lerp_mode": "catmullrom"
						},
						"0.4375": {
							"post": {
								"vector": [0, 0.88, 0]
							},
							"lerp_mode": "catmullrom"
						},
						"0.5833": {
							"post": {
								"vector": [0, 0, 0]
							},
							"lerp_mode": "catmullrom"
						}
					}
				},
				"bone7": {
					"rotation": {
						"0.0": {
							"post": {
								"vector": [0, 0, 0]
							},
							"lerp_mode": "catmullrom"
						},
						"0.1458": {
							"post": {
								"vector": [-45, 0, 0]
							},
							"lerp_mode": "catmullrom"
						},
						"0.3125": {
							"post": {
								"vector": [0, 0, 0]
							},
							"lerp_mode": "catmullrom"
						},
						"0.4375": {
							"post": {
								"vector": [4.25418, 44.92096, 3.00678]
							},
							"lerp_mode": "catmullrom"
						},
						"0.5833": {
							"post": {
								"vector": [0, 0, 0]
							},
							"lerp_mode": "catmullrom"
						}
					}
				},
				"bone6": {
					"rotation": {
						"0.0": {
							"post": {
								"vector": [0, 0, 0]
							},
							"lerp_mode": "catmullrom"
						},
						"0.1458": {
							"post": {
								"vector": [45, 0, 0]
							},
							"lerp_mode": "catmullrom"
						},
						"0.3125": {
							"post": {
								"vector": [0, 0, 0]
							},
							"lerp_mode": "catmullrom"
						},
						"0.4375": {
							"post": {
								"vector": [-25.75849, -22.46724, 1.24639]
							},
							"lerp_mode": "catmullrom"
						},
						"0.5833": {
							"post": {
								"vector": [0, 0, 0]
							},
							"lerp_mode": "catmullrom"
						}
					}
				},
				"bone4": {
					"rotation": {
						"0.0": {
							"post": {
								"vector": [0, 0, 0]
							},
							"lerp_mode": "catmullrom"
						},
						"0.1875": {
							"post": {
								"vector": [10, 0, -27.5]
							},
							"lerp_mode": "catmullrom"
						},
						"0.3333": {
							"post": {
								"vector": [-40, 0, -27.5]
							},
							"lerp_mode": "catmullrom"
						},
						"0.5625": {
							"post": {
								"vector": [0, 0, 0]
							},
							"lerp_mode": "catmullrom"
						}
					}
				},
				"bone3": {
					"rotation": {
						"0.0": {
							"post": {
								"vector": [0, 0, 0]
							},
							"lerp_mode": "catmullrom"
						},
						"0.125": {
							"post": {
								"vector": [1.41924, -9.86682, 27.68896]
							},
							"lerp_mode": "catmullrom"
						},
						"0.2292": {
							"post": {
								"vector": [-100.64496, 27.13997, -5.68694]
							},
							"lerp_mode": "catmullrom"
						},
						"0.3125": {
							"post": {
								"vector": [-77.10842, 8.29846, 91.45352]
							},
							"lerp_mode": "catmullrom"
						},
						"0.4375": {
							"post": {
								"vector": [57.89158, 8.29846, 91.45352]
							},
							"lerp_mode": "catmullrom"
						},
						"0.5625": {
							"post": {
								"vector": [0, 0, 0]
							},
							"lerp_mode": "catmullrom"
						}
					}
				},
				"bone5": {
					"rotation": {
						"0.0": {
							"post": {
								"vector": [0, 0, 0]
							},
							"lerp_mode": "catmullrom"
						},
						"0.1667": {
							"post": {
								"vector": [11.4271, -5.04349, -13.66203]
							},
							"lerp_mode": "catmullrom"
						},
						"0.3125": {
							"post": {
								"vector": [3.77984, 6.44322, 3.90899]
							},
							"lerp_mode": "catmullrom"
						},
						"0.4375": {
							"post": {
								"vector": [6.34239, 11.68667, 3.92057]
							},
							"lerp_mode": "catmullrom"
						},
						"0.5625": {
							"post": {
								"vector": [0, 0, 0]
							},
							"lerp_mode": "catmullrom"
						}
					}
				},
				"bone8": {
					"rotation": {
						"0.0": {
							"post": {
								"vector": [0, 0, 0]
							},
							"lerp_mode": "catmullrom"
						},
						"0.2083": {
							"post": {
								"vector": [-10, 0, 5]
							},
							"lerp_mode": "catmullrom"
						},
						"0.3958": {
							"post": {
								"vector": [0.35256, -43.44039, -6.24326]
							},
							"lerp_mode": "catmullrom"
						},
						"0.5625": {
							"post": {
								"vector": [0, 0, 0]
							},
							"lerp_mode": "catmullrom"
						}
					},
					"position": {
						"0.0": {
							"post": {
								"vector": [0, 0, 0]
							},
							"lerp_mode": "catmullrom"
						},
						"0.1042": {
							"post": {
								"vector": [0, 0.75, 0]
							},
							"lerp_mode": "catmullrom"
						},
						"0.3542": {
							"post": {
								"vector": [0, -0.5, 0]
							},
							"lerp_mode": "catmullrom"
						},
						"0.5625": {
							"post": {
								"vector": [0, 0, 0]
							},
							"lerp_mode": "catmullrom"
						}
					}
				}
			}
		}
	},
	"geckolib_format_version": 2
}